scripts/__init__.py
blitzkit-0.0.10.dist-info/METADATA
blitzkit-0.0.10.dist-info/WHEEL
blitzkit-0.0.10.dist-info/entry_points.txt
blitzkit-0.0.10.dist-info/top_level.txt
blitzkit-0.0.10.dist-info/RECORD
