Metadata-Version: 2.4
Name: blitzkit
Version: 0.0.10
Summary: BlitzKit is a command-line tool that helps student developers automate full-stack project setup. It generates a clean, organized folder structure with starter files to help you get started fast.
Home-page: https://github.com/lennythecreator/BlitzKit/tree/main
Author: Lenny Uwaeme
Author-email: lenyeuwame@gmail.com
Classifier: Programming Language :: Python :: 3.11
Classifier: Operating System :: OS Independent
Requires-Dist: argparse
Requires-Dist: pyfiglet
Dynamic: author
Dynamic: author-email
Dynamic: classifier
Dynamic: description
Dynamic: description-content-type
Dynamic: home-page
Dynamic: requires-dist
Dynamic: summary
